Workbook

Sheet Cover
A2: APPLE INC.
A4: Integrated Three-Statement Financial Model & DCF Valuation
B14: Model Components | H14: Key Assumptions
B15: 1. Historical Financial Analysis | H15: Assumption | I15: Value
B16: 2. Assumptions & Forecast Drivers | H16: Forecast Period | I16: FY2026E–FY2030E
B17: 3. Income Statement Forecast | H17: WACC | I17: 0.09
B18: 4. Balance Sheet Forecast | H18: Terminal Growth Rate | I18: 0.025
B19: 5. Cash Flow Statement Forecast | H19: Valuation Method | I19: DCF (Gordon Growth)
B20: 6. Supporting Schedules | H20: Currency | I20: USD Millions
B21: 7. Model Checks
B22: 8. DCF Valuation
B23: 9. Sensitivity Analysis
D25: VALUATION SUMMARY
C27: Base Case Enterprise Value $1,520,796 Million
D31: Data Source
E32: Apple Inc. Form 10-K Filings (SEC EDGAR Database)
F35: Prepared By | G35: Date | H35: Purpose
F36: SMRITI K NARKHEDE | G36: 46174 | H36: Academic Finance Project

Sheet Historical 
A1: Item | B1: FY2023 | C1: FY2024 | D1: FY2025
A2: Revenue | B2: 383285 | C2: 391035 | D2: 416161
A3: Cost of Revenue | B3: 214137 | C3: 210352 | D3: 220960
A4: Gross Profit | B4: 169148 | C4: 180683 | D4: 195201
A5: R&D | B5: 29915 | C5: 31370 | D5: 34550
A6: SG&A | B6: 24932 | C6: 26097 | D6: 27601
A7: Operating Income | B7: 114301 | C7: 123216 | D7: 133050
A8: Other Income/(Expense) | B8: 565 | C8: -565 | D8: -266
A9: Pre-Tax Income | B9: 114866 | C9: 122651 | D9: 132784
A10: Tax Provision | B10: 16741 | C10: 29749 | D10: 20719
A11: Net Income | B11: 96995 | C11: 93736 | D11: 112010
A12: Depreciation & Amortization | B12: 8341 | C12: 8314 | D12: 8571
A13: Capex | B13: -10959 | C13: -12715 | D13: -9447
A15: Source: Apple's Annual Reports (Form 10-K) filed with the U.S. Securities and Exchange Commission (SEC).

Sheet Assumptions
A1: BLOCK 1 — REVENUE ASSUMPTIONS | F1: BLOCK 2 — MARGIN ASSUMPTIONS | J1: BLOCK 3 — TAX ASSUMPTION | N1: BLOCK 4 — INVESTMENT ASSUMPTIONS | Q1: BLOCK 5 — WORKING CAPITAL ASSUMPTIONS | U1: BLOCK 6 — VALUATION ASSUMPTIONS (we use later for DCF)
U2: Driver | V2: Value
A3: Driver | B3: Value | F3: Driver | G3: Value | J3: Driver | K3: Value | N3: Driver | O3: Value | Q3: Driver | R3: Value | U3: WACC | V3: 0.09
A4: Revenue Growth FY2026 | B4: 0.06 | F4: COGS % Revenue | G4: 0.58 | J4: Tax Rate | K4: 0.21 | N4: Capex % Revenue | O4: 0.05 | Q4: AR Days | R4: 30 | U4: Terminal Growth Rate | V4: 0.025
A5: Revenue Growth FY2027 | B5: 0.06 | F5: R&D % Revenue | G5: 0.07 | N5: Depreciation % Revenue | O5: 0.03 | Q5: Inventory Days | R5: 10
A6: Revenue Growth FY2028 | B6: 0.055 | F6: SG&A % Revenue | G6: 0.06 | J6: Standard US corporate tax assumption | Q6: AP Days | R6: 40
A7: Revenue Growth FY2029 | B7: 0.05 | N7: Interpretation:
A8: Revenue Growth FY2030 | B8: 0.045 | F8: Interpretation: | N8: Capex = reinvestment into infrastructure | Q8: Meaning:
F9: Lower margins = cost pressure | N9: Depreciation = accounting expense spread | Q9: AR = how fast Apple collects cash
A10: Apple is a mature company → growth slows over time. | F10: Stable for Apple (important insight in interviews) | Q10: AP = how long Apple delays payments
Q11: Inventory = how long stock sits
A12: Revenue forecast:

Sheet Income Statement
A1: Item | B1: FY2023A | C1: FY2024A | D1: FY2025A | E1: FY2026E | F1: FY2027E | G1: FY2028E | H1: FY2029E | I1: FY2030E
A2: Revenue | B2: ='Historical '!B2 -> 383285 | C2: ='Historical '!C2 -> 391035 | D2: ='Historical '!D2 -> 416161 | E2: =D2*(1+Assumptions!B4) -> 441130.66 | F2: =E2*(1+Assumptions!B5) -> 467598.5 | G2: =F2*(1+Assumptions!B6) -> 493316.42 | H2: =G2*(1+Assumptions!B7) -> 517982.24 | I2: =H2*(1+Assumptions!B8) -> 541291.44
A3: Cost of Revenue | B3: ='Historical '!B3 -> 214137 | C3: ='Historical '!C3 -> 210352 | D3: ='Historical '!D3 -> 220960 | E3: =E2*Assumptions!G4 -> 255855.78 | F3: =F2*Assumptions!G4 -> 271207.13 | G3: =G2*Assumptions!G4 -> 286123.52 | H3: =H2*Assumptions!G4 -> 300429.7 | I3: =I2*Assumptions!G4 -> 313949.03
A4: Gross Profit | B4: ='Historical '!B4 -> 169148 | C4: ='Historical '!C4 -> 180683 | D4: ='Historical '!D4 -> 195201 | E4: =E2-E3 -> 185274.88 | F4: =F2-F3 -> 196391.37 | G4: =G2-G3 -> 207192.9 | H4: =H2-H3 -> 217552.54 | I4: =I2-I3 -> 227342.4
A5: R&D | B5: ='Historical '!B5 -> 29915 | C5: ='Historical '!C5 -> 31370 | D5: ='Historical '!D5 -> 34550 | E5: =E2*Assumptions!G5 -> 30879.146 | F5: =F2*Assumptions!G5 -> 32731.895 | G5: =G2*Assumptions!G5 -> 34532.149 | H5: =H2*Assumptions!G5 -> 36258.757 | I5: =I2*Assumptions!G5 -> 37890.401
A6: SG&A | B6: ='Historical '!B6 -> 24932 | C6: ='Historical '!C6 -> 26097 | D6: ='Historical '!D6 -> 27601 | E6: =E2*Assumptions!G6 -> 26467.84 | F6: =F2*Assumptions!G6 -> 28055.91 | G6: =G2*Assumptions!G6 -> 29598.985 | H6: =H2*Assumptions!G6 -> 31078.934 | I6: =I2*Assumptions!G6 -> 32477.486
A7: Operating Income | B7: ='Historical '!B7 -> 114301 | C7: ='Historical '!C7 -> 123216 | D7: ='Historical '!D7 -> 133050 | E7: =E4-E5-E6 -> 127927.89 | F7: =F4-F5-F6 -> 135603.56 | G7: =G4-G5-G6 -> 143061.76 | H7: =H4-H5-H6 -> 150214.85 | I7: =I4-I5-I6 -> 156974.52
A8: Other Income/(Expense) | B8: ='Historical '!B8 -> 565 | C8: ='Historical '!C8 -> -565 | D8: ='Historical '!D8 -> -266 | E8: =-300 -> -300 | F8: =-300 -> -300 | G8: =-300 -> -300 | H8: =-300 -> -300 | I8: =-300 -> -300
A9: Pre-Tax Income | B9: ='Historical '!B9 -> 114866 | C9: ='Historical '!C9 -> 122651 | D9: ='Historical '!D9 -> 132784 | E9: =E7+E8 -> 127627.89 | F9: =F7+F8 -> 135303.56 | G9: =G7+G8 -> 142761.76 | H9: =H7+H8 -> 149914.85 | I9: =I7+I8 -> 156674.52
A10: Tax Provision | B10: ='Historical '!B10 -> 16741 | C10: ='Historical '!C10 -> 29749 | D10: ='Historical '!D10 -> 20719 | E10: =E9*Assumptions!K4 -> 26801.857 | F10: =F9*Assumptions!K4 -> 28413.749 | G10: =G9*Assumptions!K4 -> 29979.97 | H10: =H9*Assumptions!K4 -> 31482.118 | I10: =I9*Assumptions!K4 -> 32901.649
A11: Net Income | B11: ='Historical '!B11 -> 96995 | C11: ='Historical '!C11 -> 93736 | D11: ='Historical '!D11 -> 112010 | E11: =E9-E10 -> 100826.03 | F11: =F9-F10 -> 106889.82 | G11: =G9-G10 -> 112781.79 | H11: =H9-H10 -> 118432.73 | I11: =I9-I10 -> 123772.87
A12: Depreciation & Amortization | B12: ='Historical '!B12 -> 8341 | C12: ='Historical '!C12 -> 8314 | D12: ='Historical '!D12 -> 8571 | E12: =E2*Assumptions!O5 -> 13233.92 | F12: =F2*Assumptions!O5 -> 14027.955 | G12: =G2*Assumptions!O5 -> 14799.493 | H12: =H2*Assumptions!O5 -> 15539.467 | I12: =I2*Assumptions!O5 -> 16238.743
A13: CapEx | B13: ='Historical '!B13 -> -10959 | C13: ='Historical '!C13 -> -12715 | D13: ='Historical '!D13 -> -9447 | E13: =-E2*Assumptions!O4 -> -22056.533 | F13: =-F2*Assumptions!O4 -> -23379.925 | G13: =-G2*Assumptions!O4 -> -24665.821 | H13: =-H2*Assumptions!O4 -> -25899.112 | I13: =-I2*Assumptions!O4 -> -27064.572

Sheet Balance Sheet
A1: Item | B1: FY2023A | C1: FY2024A | D1: FY2025A | E1: FY2026E | F1: FY2027E | G1: FY2028E | H1: FY2029E | I1: FY2030E
A2: Cash & Equivalents | B2: 29965 | C2: 29943 | D2: 35934 | E2: ='Cash Flow Statement'!C11 -> 215197.35 | F2: ='Cash Flow Statement'!D11 -> 311821.51 | G2: ='Cash Flow Statement'!E11 -> 413849.18 | H2: ='Cash Flow Statement'!F11 -> 521070.79 | I2: ='Cash Flow Statement'!G11 -> 633213.18
A3: Accounts Receivable | B3: 29508 | C3: 33410 | D3: 39777 | E3: ='Income Statement'!E2*Assumptions!R4/365 -> 36257.315 | F3: ='Income Statement'!F2*Assumptions!R4/365 -> 38432.753 | G3: ='Income Statement'!G2*Assumptions!R4/365 -> 40546.555 | H3: ='Income Statement'!H2*Assumptions!R4/365 -> 42573.883 | I3: ='Income Statement'!I2*Assumptions!R4/365 -> 44489.707
A4: Inventory | B4: 6331 | C4: 7286 | D4: 5718 | E4: ='Income Statement'!E3*Assumptions!R5/365 -> 7009.7475 | F4: ='Income Statement'!F3*Assumptions!R5/365 -> 7430.3323 | G4: ='Income Statement'!G3*Assumptions!R5/365 -> 7839.0006 | H4: ='Income Statement'!H3*Assumptions!R5/365 -> 8230.9506 | I4: ='Income Statement'!I3*Assumptions!R5/365 -> 8601.3434
A5: Other Current Assets | B5: =B6-B2-B3-B4 -> 77762 | C5: =C6-C2-C3-C4 -> 82348 | D5: =D6-D2-D3-D4 -> 66528 | E5: =D5 -> 66528 | F5: =D5 -> 66528 | G5: =D5 -> 66528 | H5: =D5 -> 66528 | I5: =D5 -> 66528
A6: Total Current Assets | B6: 143566 | C6: 152987 | D6: 147957 | E6: =SUM(E2:E5) -> 324992.41 | F6: =SUM(F2:F5) -> 424212.6 | G6: =SUM(G2:G5) -> 528762.73 | H6: =SUM(H2:H5) -> 638403.62 | I6: =SUM(I2:I5) -> 752832.23
A7: PP&E, Net | B7: 43715 | C7: 45680 | D7: 46994 | E7: ='Supporting Schedules'!C5 -> 55816.613 | F7: ='Supporting Schedules'!D5 -> 65168.583 | G7: ='Supporting Schedules'!E5 -> 75034.912 | H7: ='Supporting Schedules'!F5 -> 85394.556 | I7: ='Supporting Schedules'!G5 -> 96220.385
A8: Other Non-Current Assets | B8: =B9-B6-B7 -> 165302 | C8: =C9-C6-C7 -> 166313 | D8: =D9-D6-D7 -> 164290 | E8: =D8 -> 164290 | F8: =E8 -> 164290 | G8: =F8 -> 164290 | H8: =G8 -> 164290 | I8: =H8 -> 164290
A9: Total Assets | B9: 352583 | C9: 364980 | D9: 359241 | E9: =E6+E7+E8 -> 545099.02 | F9: =F6+F7+F8 -> 653671.18 | G9: =G6+G7+G8 -> 768087.64 | H9: =H6+H7+H8 -> 888088.17 | I9: =I6+I7+I8 -> 1013342.6
A10: Accounts Payable | B10: 62611 | C10: 68960 | D10: 54141 | E10: ='Income Statement'!E3*Assumptions!R6/365 -> 28038.99 | F10: ='Income Statement'!F3*Assumptions!R6/365 -> 29721.329 | G10: ='Income Statement'!G3*Assumptions!R6/365 -> 31356.002 | H10: ='Income Statement'!H3*Assumptions!R6/365 -> 32923.803 | I10: ='Income Statement'!I3*Assumptions!R6/365 -> 34405.374
A11: Other Current Liabilities | B11: =B12-B10 -> 82697 | C11: =C12-C10 -> 107432 | D11: =D12-D10 -> 111490 | E11: =D11 -> 111490 | F11: =E11 -> 111490 | G11: =F11 -> 111490 | H11: =G11 -> 111490 | I11: =H11 -> 111490
A12: Total Current Liabilities | B12: 145308 | C12: 176392 | D12: 165631 | E12: =E10+E11 -> 139528.99 | F12: =F10+F11 -> 141211.33 | G12: =G10+G11 -> 142846 | H12: =H10+H11 -> 144413.8 | I12: =I10+I11 -> 145895.37
A13: Long-Term Debt | B13: 95281 | C13: 85750 | D13: 87120 | E13: =D13 -> 87120 | F13: =E13 -> 87120 | G13: =F13 -> 87120 | H13: =G13 -> 87120 | I13: =H13 -> 87120
A14: Other Non-Current Liabilities | B14: =B15-B13-B12 -> 49848 | C14: =C15-C13-C12 -> 45888 | D14: =D15-D13-D12 -> 45475 | E14: =D14 -> 45475 | F14: =E14 -> 45475 | G14: =F14 -> 45475 | H14: =G14 -> 45475 | I14: =H14 -> 45475
A15: Total Liabilities | B15: 290437 | C15: 308030 | D15: 298226 | E15: =E12+E13+E14 -> 272123.99 | F15: =F12+F13+F14 -> 273806.33 | G15: =G12+G13+G14 -> 275441 | H15: =H12+H13+H14 -> 277008.8 | I15: =I12+I13+I14 -> 278490.37
A16: Shareholders' Equity | B16: 62146 | C16: 56950 | D16: 61015 | E16: =E9-E15 -> 272975.03 | F16: =E16+'Income Statement'!F11 -> 379864.85 | G16: =F16+'Income Statement'!G11 -> 492646.64 | H16: =G16+'Income Statement'!H11 -> 611079.37 | I16: =H16+'Income Statement'!I11 -> 734852.24
A17: Total Liabilities & Equity | B17: =B15+B16 -> 352583 | C17: =C15+C16 -> 364980 | D17: =D15+D16 -> 359241 | E17: =E15+E16 -> 545099.02 | F17: =F15+F16 -> 653671.18 | G17: =G15+G16 -> 768087.64 | H17: =H15+H16 -> 888088.17 | I17: =I15+I16 -> 1013342.6
A18: Balance Check | E18: =E9-E17 -> 0 | F18: =F9-F17 -> 0 | G18: =G9-G17 -> 0 | H18: =H9-H17 -> 0 | I18: =I9-I17 -> 0

Sheet Cash Flow Statement
A1: Item | B1: FY2025A | C1: FY2026E | D1: FY2027E | E1: FY2028E | F1: FY2029E | G1: FY2030E
A2: Net Income | B2: ='Income Statement'!D11 -> 112010 | C2: ='Income Statement'!E11 -> 100826.03 | D2: ='Income Statement'!F11 -> 106889.82 | E2: ='Income Statement'!G11 -> 112781.79 | F2: ='Income Statement'!H11 -> 118432.73 | G2: ='Income Statement'!I11 -> 123772.87
A3: + Depreciation & Amortization | B3: ='Income Statement'!D12 -> 8571 | C3: ='Income Statement'!E12 -> 13233.92 | D3: ='Income Statement'!F12 -> 14027.955 | E3: ='Income Statement'!G12 -> 14799.493 | F3: ='Income Statement'!H12 -> 15539.467 | G3: ='Income Statement'!I12 -> 16238.743
A4: - Change in Accounts Receivable | B4: 0 | C4: ='Balance Sheet'!E3-'Balance Sheet'!D3 -> -3519.6855 | D4: ='Balance Sheet'!F3-'Balance Sheet'!E3 -> 2175.4389 | E4: ='Balance Sheet'!G3-'Balance Sheet'!F3 -> 2113.8014 | F4: ='Balance Sheet'!H3-'Balance Sheet'!G3 -> 2027.3277 | G4: ='Balance Sheet'!I3-'Balance Sheet'!H3 -> 1915.8247
A5: - Change in Inventory | B5: 0 | C5: ='Balance Sheet'!E4-'Balance Sheet'!D4 -> 1291.7475 | D5: ='Balance Sheet'!F4-'Balance Sheet'!E4 -> 420.58485 | E5: ='Balance Sheet'!G4-'Balance Sheet'!F4 -> 408.66828 | F5: ='Balance Sheet'!H4-'Balance Sheet'!G4 -> 391.95003 | G5: ='Balance Sheet'!I4-'Balance Sheet'!H4 -> 370.39278
A6: + Change in Accounts Payable | B6: 0 | C6: ='Balance Sheet'!E10-'Balance Sheet'!D10 -> -26102.01 | D6: ='Balance Sheet'!F10-'Balance Sheet'!E10 -> 1682.3394 | E6: ='Balance Sheet'!G10-'Balance Sheet'!F10 -> 1634.6731 | F6: ='Balance Sheet'!H10-'Balance Sheet'!G10 -> 1567.8001 | G6: ='Balance Sheet'!I10-'Balance Sheet'!H10 -> 1481.5711
A7: Cash Flow from Operations | B7: =B2+B3-B4-B5+B6 -> 120581 | C7: =C2+C3-C4-C5+C6 -> 90185.882 | D7: =D2+D3-D4-D5+D6 -> 120004.09 | E7: =E2+E3-E4-E5+E6 -> 126693.49 | F7: =F2+F3-F4-F5+F6 -> 133120.72 | G7: =G2+G3-G4-G5+G6 -> 139206.97
A8: CapEx | B8: ='Income Statement'!D13 -> -9447 | C8: ='Income Statement'!E13 -> -22056.533 | D8: ='Income Statement'!F13 -> -23379.925 | E8: ='Income Statement'!G13 -> -24665.821 | F8: ='Income Statement'!H13 -> -25899.112 | G8: ='Income Statement'!I13 -> -27064.572
A9: Free Cash Flow | B9: =B7+B8 -> 111134 | C9: =C7+C8 -> 68129.349 | D9: =D7+D8 -> 96624.162 | E9: =E7+E8 -> 102027.67 | F9: =F7+F8 -> 107221.61 | G9: =G7+G8 -> 112142.39
A10: Beginning Cash | B10: ='Balance Sheet'!D2 -> 35934 | C10: =B11 -> 147068 | D10: =C11 -> 215197.35 | E10: =D11 -> 311821.51 | F10: =E11 -> 413849.18 | G10: =F11 -> 521070.79
A11: Ending Cash | B11: =B10+B9 -> 147068 | C11: =C10+C9 -> 215197.35 | D11: =D10+D9 -> 311821.51 | E11: =E10+E9 -> 413849.18 | F11: =F10+F9 -> 521070.79 | G11: =G10+G9 -> 633213.18

Sheet Supporting Schedules
A1: Item | B1: FY2025A | C1: FY2026E | D1: FY2027E | E1: FY2028E | F1: FY2029E | G1: FY2030E
A2: Beginning PP&E | B2: 46994 | C2: =B5 -> 46994 | D2: =C5 -> 55816.613 | E2: =D5 -> 65168.583 | F2: =E5 -> 75034.912 | G2: =F5 -> 85394.556
A3: + CapEx | C3: ='Income Statement'!E13 -> -22056.533 | D3: ='Income Statement'!F13 -> -23379.925 | E3: ='Income Statement'!G13 -> -24665.821 | F3: ='Income Statement'!H13 -> -25899.112 | G3: ='Income Statement'!I13 -> -27064.572
A4: - Depreciation | C4: ='Income Statement'!E12 -> 13233.92 | D4: ='Income Statement'!F12 -> 14027.955 | E4: ='Income Statement'!G12 -> 14799.493 | F4: ='Income Statement'!H12 -> 15539.467 | G4: ='Income Statement'!I12 -> 16238.743
A5: Ending PP&E | B5: =B2 -> 46994 | C5: =C2-C3-C4 -> 55816.613 | D5: =D2-D3-D4 -> 65168.583 | E5: =E2-E3-E4 -> 75034.912 | F5: =F2-F3-F4 -> 85394.556 | G5: =G2-G3-G4 -> 96220.385

Sheet Checks
A1: Check | B1: Result
A2: Net Income FY2023 | B2: ✔ | C2: 96995
A3: Net Income FY2024 | B3: ✔ | C3: 93736
A4: Net Income FY2025 | B4: ✔ | C4: 112010
A7: Extracted historical income statement line items from Apple’s Consolidated Statements of Operations in Form 10-K filings (FY2023–FY2025).
A8: Reference: | B8: https://www.sec.gov/ix?doc=/Archives/edgar/data/0000320193/000032019325000079/aapl-20250927.htm#fact-identifier-230

Sheet DCF
A1: Item | B1: FY2026E | C1: FY2027E | D1: FY2028E | E1: FY2029E | F1: FY2030E
A2: Free Cash Flow | B2: ='Cash Flow Statement'!C9 -> 68129.349 | C2: ='Cash Flow Statement'!D9 -> 96624.162 | D2: ='Cash Flow Statement'!E9 -> 102027.67 | E2: ='Cash Flow Statement'!F9 -> 107221.61 | F2: ='Cash Flow Statement'!G9 -> 112142.39
A3: Discount Factor | B3: =1/(1+Assumptions!V3)^1 -> 0.91743119 | C3: =1/(1+Assumptions!V3)^2 -> 0.84167999 | D3: =1/(1+Assumptions!V3)^3 -> 0.77218348 | E3: =1/(1+Assumptions!V3)^4 -> 0.70842521 | F3: =1/(1+Assumptions!V3)^5 -> 0.64993139
A4: Present Value of FCF | B4: =B2*B3 -> 62503.99 | C4: =C2*C3 -> 81326.624 | D4: =D2*D3 -> 78784.078 | E4: =E2*E3 -> 75958.49 | F4: =F2*F3 -> 72884.861
A7: Item | B7: Value
A8: Terminal Value | B8: =F2*(1+Assumptions!V4)/(Assumptions!V3-Assumptions!V4) -> 1768399.3
A9: PV of Terminal Value | B9: =B8*F3 -> 1149338.2
A10: Enterprise Value | B10: =SUM(B4:F4)+B8 -> 2139857.3

Sheet Sensitivity
A1: Sensitivity Analysis – Enterprise Value ($ millions)
A2: Terminal Growth ↓ / WACC → | B2: 0.08 | C2: 0.085 | D2: 0.09 | E2: 0.095 | F2: 0.1
A3: 0.02 | B3: =SUM(DCF!$B$4:$F$4)+((DCF!$F$2*(1+$A3))/(B$2-$A3))*DCF!$F$3 -> 1610500.7 | C3: =SUM(DCF!$B$4:$F$4)+((DCF!$F$2*(1+$A3))/(C$2-$A3))*DCF!$F$3 -> 1515189.7 | D3: =SUM(DCF!$B$4:$F$4)+((DCF!$F$2*(1+$A3))/(D$2-$A3))*DCF!$F$3 -> 1433494.6 | E3: =SUM(DCF!$B$4:$F$4)+((DCF!$F$2*(1+$A3))/(E$2-$A3))*DCF!$F$3 -> 1362692.2 | F3: =SUM(DCF!$B$4:$F$4)+((DCF!$F$2*(1+$A3))/(F$2-$A3))*DCF!$F$3 -> 1300740
A4: 0.025 | B4: =SUM(DCF!$B$4:$F$4)+((DCF!$F$2*(1+$A4))/(B$2-$A4))*DCF!$F$3 -> 1729766.8 | C4: =SUM(DCF!$B$4:$F$4)+((DCF!$F$2*(1+$A4))/(C$2-$A4))*DCF!$F$3 -> 1616574.4 | D4: =SUM(DCF!$B$4:$F$4)+((DCF!$F$2*(1+$A4))/(D$2-$A4))*DCF!$F$3 -> 1520796.2 | E4: =SUM(DCF!$B$4:$F$4)+((DCF!$F$2*(1+$A4))/(E$2-$A4))*DCF!$F$3 -> 1438700.7 | F4: =SUM(DCF!$B$4:$F$4)+((DCF!$F$2*(1+$A4))/(F$2-$A4))*DCF!$F$3 -> 1367551.1
A5: 0.03 | B5: =SUM(DCF!$B$4:$F$4)+((DCF!$F$2*(1+$A5))/(B$2-$A5))*DCF!$F$3 -> 1872886.2 | C5: =SUM(DCF!$B$4:$F$4)+((DCF!$F$2*(1+$A5))/(C$2-$A5))*DCF!$F$3 -> 1736392.7 | D5: =SUM(DCF!$B$4:$F$4)+((DCF!$F$2*(1+$A5))/(D$2-$A5))*DCF!$F$3 -> 1622648.2 | E5: =SUM(DCF!$B$4:$F$4)+((DCF!$F$2*(1+$A5))/(E$2-$A5))*DCF!$F$3 -> 1526402.8 | F5: =SUM(DCF!$B$4:$F$4)+((DCF!$F$2*(1+$A5))/(F$2-$A5))*DCF!$F$3 -> 1443906.7
A6: 0.035 | B6: =SUM(DCF!$B$4:$F$4)+((DCF!$F$2*(1+$A6))/(B$2-$A6))*DCF!$F$3 -> 2047809.9 | C6: =SUM(DCF!$B$4:$F$4)+((DCF!$F$2*(1+$A6))/(C$2-$A6))*DCF!$F$3 -> 1880174.7 | D6: =SUM(DCF!$B$4:$F$4)+((DCF!$F$2*(1+$A6))/(D$2-$A6))*DCF!$F$3 -> 1743018.6 | E6: =SUM(DCF!$B$4:$F$4)+((DCF!$F$2*(1+$A6))/(E$2-$A6))*DCF!$F$3 -> 1628721.9 | F6: =SUM(DCF!$B$4:$F$4)+((DCF!$F$2*(1+$A6))/(F$2-$A6))*DCF!$F$3 -> 1532009.3
A7: 0.04 | B7: =SUM(DCF!$B$4:$F$4)+((DCF!$F$2*(1+$A7))/(B$2-$A7))*DCF!$F$3 -> 2266464.4 | C7: =SUM(DCF!$B$4:$F$4)+((DCF!$F$2*(1+$A7))/(C$2-$A7))*DCF!$F$3 -> 2055908.2 | D7: =SUM(DCF!$B$4:$F$4)+((DCF!$F$2*(1+$A7))/(D$2-$A7))*DCF!$F$3 -> 1887463.2 | E7: =SUM(DCF!$B$4:$F$4)+((DCF!$F$2*(1+$A7))/(E$2-$A7))*DCF!$F$3 -> 1749644.5 | F7: =SUM(DCF!$B$4:$F$4)+((DCF!$F$2*(1+$A7))/(F$2-$A7))*DCF!$F$3 -> 1634795.6
